td_ml_mta/__init__.py
td_ml_mta/markov.py
td_ml_mta/shapley.py
td_ml_mta-0.0.15.dist-info/METADATA
td_ml_mta-0.0.15.dist-info/WHEEL
td_ml_mta-0.0.15.dist-info/licenses/LICENSE
td_ml_mta-0.0.15.dist-info/RECORD
