Metadata-Version: 2.1
Name: td_ml_mta
Version: 0.0.15
Summary: Multi-Touch Attribution using Shapley and Markov chains 
Project-URL: Homepage, https://github.com/treasure-data-ps/td_ml_libraries/tree/main/td_ml_mta
Project-URL: Bug Tracker, https://github.com/treasure-data-ps/td_ml_libraries/tree/main/td_ml_mta
Author-email: Gurbaksh Sharma <gurumail10@gmail.com>
License: Copyright © 2022 Treasure Data, Inc. (or its affiliates). All rights reserved
License-File: LICENSE
Classifier: Operating System :: OS Independent
Classifier: Programming Language :: Python :: 3
Requires-Python: >=3.8
